app/__init__.py
app/main.py
app/core/__init__.py
app/core/auth.py
app/core/imports.py
app/core/manifest.py
app/core/prompts_provider.py
app/core/registry.py
app/core/settings.py
app/core/templates.py
app/services/__init__.py
app/services/constants.py
app/services/data_product/__init__.py
app/services/data_product/models/__init__.py
app/services/data_product/models/add_delivery_methods_to_data_product.py
app/services/data_product/models/attach_business_domain_to_data_product.py
app/services/data_product/models/attach_contract_to_data_product.py
app/services/data_product/models/create_data_product_from_catalog.py
app/services/data_product/models/create_url_data_product.py
app/services/data_product/models/find_delivery_methods_based_on_connection.py
app/services/data_product/models/get_assets_from_catalog.py
app/services/data_product/models/publish_data_product.py
app/services/data_product/models/search_data_products.py
app/services/data_product/tools/__init__.py
app/services/data_product/tools/add_delivery_methods_to_data_product.py
app/services/data_product/tools/attach_business_domain_to_data_product.py
app/services/data_product/tools/attach_contract_to_data_product.py
app/services/data_product/tools/create_data_product_from_catalog.py
app/services/data_product/tools/create_url_data_product.py
app/services/data_product/tools/find_delivery_methods_based_on_connection.py
app/services/data_product/tools/get_assets_from_catalog.py
app/services/data_product/tools/publish_data_product.py
app/services/data_product/tools/search_data_products.py
app/services/data_product/utils/__init__.py
app/services/data_product/utils/common_utils.py
app/services/data_product/utils/data_product_creation_utils.py
app/services/data_protection_rules/__init__.py
app/services/data_protection_rules/models/__init__.py
app/services/data_protection_rules/models/create_rule.py
app/services/data_protection_rules/tools/__init__.py
app/services/data_protection_rules/tools/create_rule.py
rsamal_data_intelligence_mcp_server-0.0.5.dist-info/licenses/LICENSE
rsamal_data_intelligence_mcp_server-0.0.5.dist-info/METADATA
rsamal_data_intelligence_mcp_server-0.0.5.dist-info/WHEEL
rsamal_data_intelligence_mcp_server-0.0.5.dist-info/entry_points.txt
rsamal_data_intelligence_mcp_server-0.0.5.dist-info/top_level.txt
rsamal_data_intelligence_mcp_server-0.0.5.dist-info/RECORD
